ChangeLog
LICENSE
MANIFEST.in
README
TODO
setup.cfg
setup.py
docs/ACKNOWLEDGEMENTS.txt
docs/FOOTNOTES.txt
docs/HISTORY.txt
docs/PRELUDE.txt
examples/example1.png
examples/example1.py
examples/example2.png
examples/example2.py
examples/example3-large.png
examples/example3.png
examples/example3.py
examples/example4-large.png
examples/example4.png
examples/example4.py
examples/example5-10800-large.png
examples/example5-10800.png
examples/example5-259200-large.png
examples/example5-259200.png
examples/example5-43200-large.png
examples/example5-43200.png
examples/example5-86400-large.png
examples/example5-86400.png
examples/example5.py
pyrrd/__init__.py
pyrrd/exceptions.py
pyrrd/graph.py
pyrrd/mapper.py
pyrrd/meta.py
pyrrd/node.py
pyrrd/rrd.py
pyrrd/backend/__init__.py
pyrrd/backend/bindings.py
pyrrd/backend/common.py
pyrrd/backend/external.py
pyrrd/backend/native/__init__.py
pyrrd/backend/native/format.py
pyrrd/backend/tests/__init__.py
pyrrd/backend/tests/test_bindings.py
pyrrd/backend/tests/test_external.py
pyrrd/testing/__init__.py
pyrrd/testing/base.py
pyrrd/testing/dump.py
pyrrd/testing/suite.py
pyrrd/tests/__init__.py
pyrrd/tests/test_mapper.py
pyrrd/tests/test_node.py
pyrrd/tests/test_rrd.py
pyrrd/util/__init__.py
pyrrd/util/dist.py
pyrrd_fix.egg-info/PKG-INFO
pyrrd_fix.egg-info/SOURCES.txt
pyrrd_fix.egg-info/dependency_links.txt
pyrrd_fix.egg-info/top_level.txt