Metadata-Version: 1.0
Name: pyrrd-fix
Version: 0.1.1
Summary: bug fixed for pyrrd
Home-page: http://code.google.com/p/pyrrd/
Author: Duncan McGreggor
Author-email: duncan@canonical.com
License: BSD
Platform: UNKNOWN
Classifier: Development Status :: 4 - Beta
Classifier: Intended Audience :: Developers
Classifier: Intended Audience :: Information Technology
Classifier: Intended Audience :: System Administrators
Classifier: Programming Language :: Python
Classifier: Topic :: Database
Classifier: Topic :: Database :: Front-Ends
Classifier: Topic :: Multimedia :: Graphics
Classifier: Topic :: System :: Networking :: Monitoring
Classifier: Topic :: System :: Systems Administration
Classifier: License :: OSI Approved :: BSD License
